lxman/__init__.py
lxman/registry.py
lxman/cli/__init__.py
lxman/cli/__main__.py
lxman/cli/config.py
lxman/cli/extractor_params.py
lxman/cli/fs.py
lxman/cli/log.py
lxman/cli/manage.py
lxman/cli/page.py
lxman/cli/settings.py
lxman/sources/__init__.py
lxman/sources/docker.py
lxman/sources/downloader.py
lxman/sources/file.py
lxman/sources/source.py
lxman/sources/uri.py
lxman/unpack/__init__.py
lxman/unpack/dir.py
lxman/unpack/extractor.py
lxman/unpack/tar.py
lxman/vendor/__init__.py
lxman/vendor/ntfsea.cp36-win_amd64.dll
lxman/vendor/ntfsea.py
lxman/vendor/ntfsutils.py
lxman-0.1.0.dist-info/DESCRIPTION.rst
lxman-0.1.0.dist-info/METADATA
lxman-0.1.0.dist-info/RECORD
lxman-0.1.0.dist-info/WHEEL
lxman-0.1.0.dist-info/entry_points.txt
lxman-0.1.0.dist-info/metadata.json
lxman-0.1.0.dist-info/top_level.txt
